gray_elf.py
gray_elf-0.2.0.dist-info/METADATA
gray_elf-0.2.0.dist-info/WHEEL
gray_elf-0.2.0.dist-info/top_level.txt
gray_elf-0.2.0.dist-info/RECORD
