Metadata-Version: 2.1
Name: gray-elf
Version: 0.2.0
Summary: Python logging formatter and handlers for Graylog Extended Log Format (GELF)
Home-page: https://github.com/ods/gray-elf
Author: Denis Otkidach
Author-email: denis.otkidach@gmail.com
License: MIT
Platform: UNKNOWN
